vista/__init__.py
vista/__main__.py
vista/app.py
vista/algorithms/__init__.py
vista/algorithms/background_removal/__init__.py
vista/algorithms/background_removal/robust_pca.py
vista/algorithms/background_removal/temporal_median.py
vista/algorithms/detectors/__init__.py
vista/algorithms/detectors/cfar.py
vista/algorithms/detectors/threshold.py
vista/algorithms/enhancement/__init__.py
vista/algorithms/enhancement/coadd.py
vista/algorithms/trackers/__init__.py
vista/algorithms/trackers/kalman_tracker.py
vista/algorithms/trackers/network_flow_tracker.py
vista/algorithms/trackers/simple_tracker.py
vista/algorithms/trackers/tracklet_tracker.py
vista/algorithms/tracks/__init__.py
vista/algorithms/tracks/extraction.py
vista/algorithms/tracks/interpolation.py
vista/algorithms/tracks/savitzky_golay.py
vista/aoi/__init__.py
vista/aoi/aoi.py
vista/detections/__init__.py
vista/detections/detector.py
vista/features/__init__.py
vista/features/feature.py
vista/icons/__init__.py
vista/icons/create_detection_dark.png
vista/icons/create_detection_light.png
vista/icons/create_track_dark.png
vista/icons/create_track_light.png
vista/icons/draw_roi_dark.png
vista/icons/draw_roi_light.png
vista/icons/geodetic_tooltip.png
vista/icons/lasso_select_dark.png
vista/icons/lasso_select_light.png
vista/icons/logo-small.jpg
vista/icons/logo.jpg
vista/icons/pixel_value_dark.png
vista/icons/pixel_value_light.png
vista/icons/select_detections_dark.png
vista/icons/select_detections_light.png
vista/icons/select_track_dark.png
vista/icons/select_track_light.png
vista/imagery/__init__.py
vista/imagery/imagery.py
vista/sensors/__init__.py
vista/sensors/sampled_sensor.py
vista/sensors/sensor.py
vista/simulate/__init__.py
vista/simulate/simulation.py
vista/simulate/data/__init__.py
vista/simulate/data/earth_image.png
vista/tracks/__init__.py
vista/tracks/track.py
vista/transforms/__init__.py
vista/transforms/arf.py
vista/transforms/earth_intersection.py
vista/transforms/polynomials.py
vista_imagery-1.9.0.dist-info/licenses/LICENSE
vista_imagery-1.9.0.dist-info/METADATA
vista_imagery-1.9.0.dist-info/WHEEL
vista_imagery-1.9.0.dist-info/entry_points.txt
vista_imagery-1.9.0.dist-info/top_level.txt
vista_imagery-1.9.0.dist-info/RECORD
