Metadata-Version: 2.4
Name: vista-imagery
Version: 1.9.0
Summary: A PyQt6-based desktop application for viewing, analyzing, and managing multi-frame imagery datasets along with associated detection and track overlays
Author-email: Stephen Hartzell <shartzell@awetomaton.com>
Maintainer-email: Stephen Hartzell <shartzell@awetomaton.com>
License: MIT
Project-URL: Homepage, https://github.com/awetomaton/VISTA
Project-URL: Repository, https://github.com/awetomaton/VISTA
Project-URL: Issues, https://github.com/awetomaton/VISTA/issues
Project-URL: Documentation, https://awetomaton.github.io/VISTA/
Keywords: VISTA,tracking,detection,imagery,PyQt6,scientific,analysis
Classifier: Development Status :: 4 - Beta
Classifier: Intended Audience :: Science/Research
Classifier: License :: OSI Approved :: MIT License
Classifier: Operating System :: OS Independent
Classifier: Programming Language :: Python :: 3
Classifier: Programming Language :: Python :: 3.13
Classifier: Topic :: Scientific/Engineering :: Image Processing
Classifier: Topic :: Scientific/Engineering :: Visualization
Classifier: Environment :: X11 Applications :: Qt
Requires-Python: >=3.9
License-File: LICENSE
Requires-Dist: astropy
Requires-Dist: darkdetect
Requires-Dist: h5py
Requires-Dist: numpy
Requires-Dist: pandas
Requires-Dist: PyQt6
Requires-Dist: pyqtgraph
Requires-Dist: pyshp
Requires-Dist: scikit-image
Requires-Dist: scipy
Requires-Dist: shapely
Provides-Extra: dev
Requires-Dist: pytest>=7.0; extra == "dev"
Requires-Dist: pytest-qt; extra == "dev"
Requires-Dist: black; extra == "dev"
Requires-Dist: ruff; extra == "dev"
Provides-Extra: docs
Requires-Dist: sphinx<9.0,>=7.0; extra == "docs"
Requires-Dist: furo>=2024.1.29; extra == "docs"
Requires-Dist: sphinx-autosummary-accessors>=2023.4.0; extra == "docs"
Requires-Dist: sphinx-multiversion>=0.2.4; extra == "docs"
Dynamic: license-file
